PMMP/__init__.py
PMMP/main.py
PMMP-0.0.7.1.dist-info/LICENSE
PMMP-0.0.7.1.dist-info/METADATA
PMMP-0.0.7.1.dist-info/WHEEL
PMMP-0.0.7.1.dist-info/top_level.txt
PMMP-0.0.7.1.dist-info/RECORD
