Metadata-Version: 2.1
Name: PMMP
Version: 0.0.7.1
Summary: PMMP is a math library
Author: PlayfulMathematician
Project-URL: Homepage, https://github.com/PlayfulMathematician/PMMP
Project-URL: Bug Tracker, https://github.com/PlayfulMathematician/PMMP/issues
Classifier: Programming Language :: Python :: 3
Classifier: Operating System :: OS Independent
Requires-Python: >=3.9
License-File: LICENSE
